setup.py
python_widerface.egg-info/PKG-INFO
python_widerface.egg-info/SOURCES.txt
python_widerface.egg-info/dependency_links.txt
python_widerface.egg-info/top_level.txt
wider/__init__.py
wider/loader.py
wider/examples/example.py
wider/examples/requirement.txt