Metadata-Version: 1.1
Name: python-widerface
Version: 0.2.1
Summary: Simple WIDERFACE data parser written in python
Home-page: https://github.com/twmht/python-widerface
Author: Ming Hsaun Tu
Author-email: qrnnis2623891@gmail.com
License: Apache Software License
Platform: UNKNOWN
Classifier: Development Status :: 5 - Production/Stable
Classifier: Intended Audience :: Developers
Classifier: Operating System :: OS Independent
Classifier: Programming Language :: Python
